README.rst
setup.py
examples/__init__.py
examples/router_request_example.py
examples/router_session_example.py
examples/stackoverflow_css_crawler.py
examples/stackoverflow_example_crawler.py
examples/stackoverflow_three_level_crawler.py
examples/stackoverflow_two_level_crawler.py
examples/wikimedia_fallback_list_example.py
examples/wikimedia_file_example.py
examples/wikimedia_search_results_crawler.py
examples/wikipedia_fallback_list_example.py
examples/wikipedia_related_topics_crawler.py
tests/__init__.py
tests/collections/__init__.py
tests/collections/test_collection_factory.py
tests/collections/test_fallback_list.py
tests/compatibility/__init__.py
tests/compatibility/test_compatibility_factory.py
tests/compatibility/object_converter/__init__.py
tests/compatibility/object_converter/test_object_converter_python2.py
tests/compatibility/object_converter/test_object_converter_python3.py
tests/compatibility/string_converter/__init__.py
tests/compatibility/string_converter/test_string_converter_python2.py
tests/compatibility/string_converter/test_string_converter_python3.py
tests/compatibility/write_opener/__init__.py
tests/compatibility/write_opener/test_write_opener_python2.py
tests/compatibility/write_opener/test_write_opener_python3.py
tests/core/__init__.py
tests/core/crawler/__init__.py
tests/core/crawler/test_crawler.py
tests/core/crawler/test_page.py
tests/core/crawler/test_page_scraper.py
tests/core/extractor/__init__.py
tests/core/extractor/test_css_selector.py
tests/core/extractor/test_element.py
tests/core/extractor/test_extractor.py
tests/core/extractor/test_extractor_css.py
tests/core/extractor/test_extractor_factory.py
tests/core/extractor/test_extractor_xpath.py
tests/files/__init__.py
tests/files/filepaths/__init__.py
tests/files/filepaths/test_filepath_splitter.py
tests/files/openers/__init__.py
tests/files/openers/test_write_opener.py
tests/files/writers/__init__.py
tests/files/writers/test_csv_writer.py
tests/files/writers/test_item_writer.py
xcrawler.egg-info/PKG-INFO
xcrawler.egg-info/SOURCES.txt
xcrawler.egg-info/dependency_links.txt
xcrawler.egg-info/requires.txt
xcrawler.egg-info/top_level.txt
