Metadata-Version: 1.1
Name: xcrawler
Version: 1.3.0
Summary: A multi-threaded, open source web crawler
Home-page: https://github.com/cardsurf/xcrawler
Author: cardsurf
Author-email: cardsurf@email.com
License: GNU GPL v2.0
Keywords: crawler,spider,scraper
Platform: Any
Classifier: Programming Language :: Python
Classifier: Programming Language :: Python :: 2
Classifier: Programming Language :: Python :: 2.7
Classifier: Programming Language :: Python :: 3
Classifier: Programming Language :: Python :: 3.4
Classifier: Operating System :: OS Independent
Classifier: License :: OSI Approved :: GNU General Public License v2 (GPLv2)
Classifier: Topic :: Internet :: WWW/HTTP
Classifier: Topic :: Internet :: WWW/HTTP :: Dynamic Content
